MANIFEST.in
README
setup.py
pam_py_linotp/__init__.py
pam_py_linotp.egg-info/PKG-INFO
pam_py_linotp.egg-info/SOURCES.txt
pam_py_linotp.egg-info/dependency_links.txt
pam_py_linotp.egg-info/not-zip-safe
pam_py_linotp.egg-info/top_level.txt
src/pam_linotp.py