Metadata-Version: 1.1
Name: pam-py-linotp
Version: 2.9.1
Summary: LinOTP python PAM module
Home-page: https://www.linotp.org
Author: KeyIdentity GmbH
Author-email: linotp@keyidentity.com
License: GPL v2, (C) KeyIdentity GmbH
Platform: UNKNOWN
Classifier: Framework :: Pylons
Classifier: License :: OSI Approved :: GNU Affero General Public License v3
Classifier: Programming Language :: Python
Classifier: Topic :: Internet
Classifier: Topic :: Security
Classifier: Topic :: System :: Systems Administration :: Authentication/Directory
